{
    "letters": "CAEILMP",
    "generation_info": {
        "path": "word_lists/scowl.txt",
        "min_word_length": 4,
        "total_letter_count": 7,
        "min_word_count": 25,
        "max_word_count": 50,
        "min_total_score": 60,
        "max_total_score": 400,
        "cap_plurals": true,
        "max_plurals": 3,
        "cap_preterite": true,
        "max_preterite": 7,
        "cap_gerunds": true,
        "max_gerunds": 5,
        "count_pangrams": 1,
        "manual_puzzle": false,
        "quality": {
            "is_valid": true,
            "s_pairs": 0,
            "ed_pairs": 0,
            "ing_pairs": 0,
            "uniqueness": 0.49
        }
    },
    "total_score": 112,
    "word_count": 32,
    "pangram_count": 1,
    "pangram_list": [
        "PIECEMEAL"
    ],
    "word_list": [
        {
            "word": "ACCLAIM",
            "score": 7,
            "pangram": false
        },
        {
            "word": "ALPACA",
            "score": 6,
            "pangram": false
        },
        {
            "word": "APIECE",
            "score": 6,
            "pangram": false
        },
        {
            "word": "CALL",
            "score": 1,
            "pangram": false
        },
        {
            "word": "CALM",
            "score": 1,
            "pangram": false
        },
        {
            "word": "CAME",
            "score": 1,
            "pangram": false
        },
        {
            "word": "CAMEL",
            "score": 5,
            "pangram": false
        },
        {
            "word": "CAMP",
            "score": 1,
            "pangram": false
        },
        {
            "word": "CAPE",
            "score": 1,
            "pangram": false
        },
        {
            "word": "CELL",
            "score": 1,
            "pangram": false
        },
        {
            "word": "CLAIM",
            "score": 5,
            "pangram": false
        },
        {
            "word": "CLAM",
            "score": 1,
            "pangram": false
        },
        {
            "word": "CLAMP",
            "score": 5,
            "pangram": false
        },
        {
            "word": "CLAP",
            "score": 1,
            "pangram": false
        },
        {
            "word": "CLIME",
            "score": 5,
            "pangram": false
        },
        {
            "word": "CLIP",
            "score": 1,
            "pangram": false
        },
        {
            "word": "EPIC",
            "score": 1,
            "pangram": false
        },
        {
            "word": "ICICLE",
            "score": 6,
            "pangram": false
        },
        {
            "word": "LACE",
            "score": 1,
            "pangram": false
        },
        {
            "word": "LICE",
            "score": 1,
            "pangram": false
        },
        {
            "word": "LILAC",
            "score": 5,
            "pangram": false
        },
        {
            "word": "MACE",
            "score": 1,
            "pangram": false
        },
        {
            "word": "MALICE",
            "score": 6,
            "pangram": false
        },
        {
            "word": "MICE",
            "score": 1,
            "pangram": false
        },
        {
            "word": "MIMIC",
            "score": 5,
            "pangram": false
        },
        {
            "word": "PACE",
            "score": 1,
            "pangram": false
        },
        {
            "word": "PALACE",
            "score": 6,
            "pangram": false
        },
        {
            "word": "PEACE",
            "score": 5,
            "pangram": false
        },
        {
            "word": "PIECE",
            "score": 5,
            "pangram": false
        },
        {
            "word": "PIECEMEAL",
            "score": 9,
            "pangram": true
        },
        {
            "word": "PLACE",
            "score": 5,
            "pangram": false
        },
        {
            "word": "PLAICE",
            "score": 6,
            "pangram": false
        }
    ]
}