{
    "letters": "GADEMNU",
    "generation_info": {
        "path": "word_lists/scowl.txt",
        "min_word_length": 4,
        "total_letter_count": 7,
        "min_word_count": 25,
        "max_word_count": 50,
        "min_total_score": 60,
        "max_total_score": 400,
        "cap_plurals": true,
        "max_plurals": 3,
        "cap_gerunds": true,
        "max_gerunds": 5,
        "count_pangrams": 1,
        "manual_puzzle": false
    },
    "total_score": 166,
    "word_count": 33,
    "pangram_count": 1,
    "pangram_list": [
        "UNDAMAGED"
    ],
    "word_list": [
        {
            "word": "ADAGE",
            "score": 5,
            "pangram": false
        },
        {
            "word": "AGED",
            "score": 1,
            "pangram": false
        },
        {
            "word": "AGENDA",
            "score": 6,
            "pangram": false
        },
        {
            "word": "DAMAGE",
            "score": 6,
            "pangram": false
        },
        {
            "word": "DAMAGED",
            "score": 7,
            "pangram": false
        },
        {
            "word": "DUNG",
            "score": 1,
            "pangram": false
        },
        {
            "word": "EDGE",
            "score": 1,
            "pangram": false
        },
        {
            "word": "EDGED",
            "score": 5,
            "pangram": false
        },
        {
            "word": "EGGED",
            "score": 5,
            "pangram": false
        },
        {
            "word": "ENGAGE",
            "score": 6,
            "pangram": false
        },
        {
            "word": "ENGAGED",
            "score": 7,
            "pangram": false
        },
        {
            "word": "GAGGED",
            "score": 6,
            "pangram": false
        },
        {
            "word": "GAME",
            "score": 1,
            "pangram": false
        },
        {
            "word": "GAMED",
            "score": 5,
            "pangram": false
        },
        {
            "word": "GAMMA",
            "score": 5,
            "pangram": false
        },
        {
            "word": "GANG",
            "score": 1,
            "pangram": false
        },
        {
            "word": "GANGED",
            "score": 6,
            "pangram": false
        },
        {
            "word": "GAUGE",
            "score": 5,
            "pangram": false
        },
        {
            "word": "GAUGED",
            "score": 6,
            "pangram": false
        },
        {
            "word": "GENE",
            "score": 1,
            "pangram": false
        },
        {
            "word": "GUMMED",
            "score": 6,
            "pangram": false
        },
        {
            "word": "GUNMAN",
            "score": 6,
            "pangram": false
        },
        {
            "word": "GUNMEN",
            "score": 6,
            "pangram": false
        },
        {
            "word": "GUNNED",
            "score": 6,
            "pangram": false
        },
        {
            "word": "MAGNUM",
            "score": 6,
            "pangram": false
        },
        {
            "word": "MANAGE",
            "score": 6,
            "pangram": false
        },
        {
            "word": "MANAGED",
            "score": 7,
            "pangram": false
        },
        {
            "word": "MANGE",
            "score": 5,
            "pangram": false
        },
        {
            "word": "MUGGED",
            "score": 6,
            "pangram": false
        },
        {
            "word": "NAGGED",
            "score": 6,
            "pangram": false
        },
        {
            "word": "NUDGE",
            "score": 5,
            "pangram": false
        },
        {
            "word": "NUDGED",
            "score": 6,
            "pangram": false
        },
        {
            "word": "UNDAMAGED",
            "score": 9,
            "pangram": true
        }
    ]
}