{
    "letters": "IACEHLR",
    "generation_info": {
        "path": "word_lists/scowl.txt",
        "min_word_length": 4,
        "total_letter_count": 7,
        "min_word_count": 25,
        "max_word_count": 50,
        "min_total_score": 60,
        "max_total_score": 400,
        "cap_plurals": true,
        "max_plurals": 3,
        "cap_gerunds": true,
        "max_gerunds": 5,
        "count_pangrams": 1,
        "manual_puzzle": false
    },
    "total_score": 230,
    "word_count": 48,
    "pangram_count": 1,
    "pangram_list": [
        "HIERARCHICAL"
    ],
    "word_list": [
        {
            "word": "AERIAL",
            "score": 6,
            "pangram": false
        },
        {
            "word": "AIRIER",
            "score": 6,
            "pangram": false
        },
        {
            "word": "ARCHAIC",
            "score": 7,
            "pangram": false
        },
        {
            "word": "ARIA",
            "score": 1,
            "pangram": false
        },
        {
            "word": "CARRIER",
            "score": 7,
            "pangram": false
        },
        {
            "word": "CHAIR",
            "score": 5,
            "pangram": false
        },
        {
            "word": "CHALICE",
            "score": 7,
            "pangram": false
        },
        {
            "word": "CHEERIER",
            "score": 8,
            "pangram": false
        },
        {
            "word": "CHIC",
            "score": 1,
            "pangram": false
        },
        {
            "word": "CHICER",
            "score": 6,
            "pangram": false
        },
        {
            "word": "CHILI",
            "score": 5,
            "pangram": false
        },
        {
            "word": "CHILL",
            "score": 5,
            "pangram": false
        },
        {
            "word": "CHILLER",
            "score": 7,
            "pangram": false
        },
        {
            "word": "CHILLI",
            "score": 6,
            "pangram": false
        },
        {
            "word": "CHILLIER",
            "score": 8,
            "pangram": false
        },
        {
            "word": "CIRCA",
            "score": 5,
            "pangram": false
        },
        {
            "word": "CIRCLE",
            "score": 6,
            "pangram": false
        },
        {
            "word": "CLERIC",
            "score": 6,
            "pangram": false
        },
        {
            "word": "CLERICAL",
            "score": 8,
            "pangram": false
        },
        {
            "word": "CLICHE",
            "score": 6,
            "pangram": false
        },
        {
            "word": "EARLIER",
            "score": 7,
            "pangram": false
        },
        {
            "word": "ECLAIR",
            "score": 6,
            "pangram": false
        },
        {
            "word": "EERIE",
            "score": 5,
            "pangram": false
        },
        {
            "word": "EERIER",
            "score": 6,
            "pangram": false
        },
        {
            "word": "HAIL",
            "score": 1,
            "pangram": false
        },
        {
            "word": "HAIR",
            "score": 1,
            "pangram": false
        },
        {
            "word": "HAIRIER",
            "score": 7,
            "pangram": false
        },
        {
            "word": "HEIR",
            "score": 1,
            "pangram": false
        },
        {
            "word": "HIERARCHICAL",
            "score": 12,
            "pangram": true
        },
        {
            "word": "HILL",
            "score": 1,
            "pangram": false
        },
        {
            "word": "HILLIER",
            "score": 7,
            "pangram": false
        },
        {
            "word": "HIRE",
            "score": 1,
            "pangram": false
        },
        {
            "word": "ICICLE",
            "score": 6,
            "pangram": false
        },
        {
            "word": "ICIER",
            "score": 5,
            "pangram": false
        },
        {
            "word": "LACIER",
            "score": 6,
            "pangram": false
        },
        {
            "word": "LAIR",
            "score": 1,
            "pangram": false
        },
        {
            "word": "LEERIER",
            "score": 7,
            "pangram": false
        },
        {
            "word": "LIAR",
            "score": 1,
            "pangram": false
        },
        {
            "word": "LICE",
            "score": 1,
            "pangram": false
        },
        {
            "word": "LILAC",
            "score": 5,
            "pangram": false
        },
        {
            "word": "RACIAL",
            "score": 6,
            "pangram": false
        },
        {
            "word": "RACIER",
            "score": 6,
            "pangram": false
        },
        {
            "word": "RAIL",
            "score": 1,
            "pangram": false
        },
        {
            "word": "RELIC",
            "score": 5,
            "pangram": false
        },
        {
            "word": "RICE",
            "score": 1,
            "pangram": false
        },
        {
            "word": "RICH",
            "score": 1,
            "pangram": false
        },
        {
            "word": "RICHER",
            "score": 6,
            "pangram": false
        },
        {
            "word": "RILE",
            "score": 1,
            "pangram": false
        }
    ]
}